README.md
setup.cfg
setup.py
pantry_cloud/__init__.py
pantry_cloud/cli.py
pantry_cloud/pantry_cloud.py
pantry_cloud.egg-info/PKG-INFO
pantry_cloud.egg-info/SOURCES.txt
pantry_cloud.egg-info/dependency_links.txt
pantry_cloud.egg-info/entry_points.txt
pantry_cloud.egg-info/requires.txt
pantry_cloud.egg-info/top_level.txt