Metadata-Version: 2.1
Name: pantry-cloud
Version: 1.2.0
Summary: Free JSON Storage API Implimentation In Python.
Home-page: https://github.com/sarvesh4396/pantry-cloud
Author: Sarvesh Kumar Dwivedi
License: MIT
Download-URL: https://github.com/sarvesh4396/pantry-cloud/archive/refs/tags/v1.2.tar.gz
Keywords: pantry_cloud,JSON,API,CLOUD STORAGE
Platform: UNKNOWN
Classifier: Development Status :: 3 - Alpha
Classifier: Topic :: Internet
Classifier: Topic :: Software Development :: Build Tools
Classifier: Topic :: Communications :: File Sharing
Classifier: Natural Language :: English
Classifier: Operating System :: OS Independent
Classifier: License :: OSI Approved :: MIT License
Classifier: Programming Language :: Python
Classifier: Programming Language :: Python :: 3 :: Only
Classifier: Programming Language :: Python :: 3
Classifier: Programming Language :: Python :: 3.7
Classifier: Programming Language :: Python :: 3.8
Classifier: Programming Language :: Python :: Implementation :: PyPy
Requires-Python: >=3.7.0
